{"type": "Feature", "id": 12515486, "geometry": {"type": "Point", "coordinates": [-14.7678, 11.5411]}, "properties": {"woe:id": 12515486, "woe:parent_id": 1563126, "woe:name": "Quebo Airport", "woe:placetype": 14, "woe:placetype_name": "Airport", "woe:lang": "ENG", "iso:country": "GW", "meta:provider": ["geoplanet:7.3.1", "geoplanet:7.3.2", "geoplanet:7.4.0", "geoplanet:7.4.1", "geoplanet:7.5.1", "geoplanet:7.5.2", "geoplanet:7.6.0", "geoplanet:7.8.1", "geoplanet:7.9.0", "geoplanet:7.10.0", "geoplanet:8.0.0", "woeplanet:8.0.0"], "meta:indexed": "2020-08-20T20:58:44.229863", "meta:updated": "2020-10-14T11:37:07.651239", "woe:hierarchy": {"continent": 24865670, "country": 23424929, "town": 0, "planet": 1, "county": 0, "suburb": 0, "state": 2346608, "region": 0, "localadmin": 0}, "woe:timezone_id": 28350689, "woe:hash": "edj3xuyrv2fp", "woe:centroid": [-14.7678, 11.5411], "geom:latitude": 11.5411, "geom:longitude": -14.7678, "geom:hash": "edj3xuyrv2fp", "woe:latitude": 11.5411, "geom:centroid": [-14.7678, 11.5411], "woe:longitude": -14.7678, "woe:repo": "woeplanet-airport-gw", "geom:area": 0.0, "woe:scale": 19}}